odoo/addons/product_supplierinfo_archive/README.rst
odoo/addons/product_supplierinfo_archive/__init__.py
odoo/addons/product_supplierinfo_archive/__manifest__.py
odoo/addons/product_supplierinfo_archive/data/ir_cron.xml
odoo/addons/product_supplierinfo_archive/i18n/product_supplierinfo_archive.pot
odoo/addons/product_supplierinfo_archive/models/__init__.py
odoo/addons/product_supplierinfo_archive/models/product_supplierinfo.py
odoo/addons/product_supplierinfo_archive/readme/CONTRIBUTORS.rst
odoo/addons/product_supplierinfo_archive/readme/DESCRIPTION.rst
odoo/addons/product_supplierinfo_archive/readme/USAGE.rst
odoo/addons/product_supplierinfo_archive/static/description/icon.png
odoo/addons/product_supplierinfo_archive/static/description/index.html
odoo/addons/product_supplierinfo_archive/tests/__init__.py
odoo/addons/product_supplierinfo_archive/tests/test_ir_cron.py
odoo/addons/product_supplierinfo_archive/views/product_views.xml
odoo14_addon_product_supplierinfo_archive-14.0.1.1.0.dist-info/METADATA
odoo14_addon_product_supplierinfo_archive-14.0.1.1.0.dist-info/WHEEL
odoo14_addon_product_supplierinfo_archive-14.0.1.1.0.dist-info/top_level.txt
odoo14_addon_product_supplierinfo_archive-14.0.1.1.0.dist-info/RECORD
